LICENSE.txt
README.rst
setup.py
rbxexecutions/__init__.py
rbxexecutions.egg-info/PKG-INFO
rbxexecutions.egg-info/SOURCES.txt
rbxexecutions.egg-info/dependency_links.txt
rbxexecutions.egg-info/requires.txt
rbxexecutions.egg-info/top_level.txt
rbxexecutions/api/__init__.py
rbxexecutions/discordbot/__init__.py
rbxexecutions/discordbot/cogs/__init__.py
rbxexecutions/discordbot/cogs/commands.py
rbxexecutions/discordbot/cogs/status.py