Metadata-Version: 2.1
Name: rbxexecutions
Version: 2
Summary: pip install rbxexecutions
Home-page: UNKNOWN
Author: MaGiXx
Author-email: email@example.com
License: MIT
Keywords: executions
Platform: UNKNOWN
License-File: LICENSE.txt
